{
    "query_image": "./datasets/flowers_102/images_discovery_all_10/087.Cyclamen_/087.Cyclamen__image_00498.jpg",
    "true_category": "087.Cyclamen ",
    "fast_result": {
        "predicted_category": "conflict",
        "confidence": 0.25186118483543396,
        "need_slow_thinking": true,
        "fused_top1": "Spring Crocus",
        "predicted_fast": "Spring Crocus",
        "img_category": "Canterbury Bells",
        "text_category": "Spring Crocus",
        "img_confidence": 0.24795114994049072,
        "text_confidence": 0.2557712197303772,
        "fused_results": [
            [
                "Spring Crocus",
                0.25642197262490907
            ],
            [
                "Magnolia",
                0.19717697655000993
            ],
            [
                "Siam Tulip",
                0.1952854731134952
            ],
            [
                "Mallow",
                0.17122837901115417
            ],
            [
                "Cape Flower",
                0.14962767893305193
            ],
            [
                "Canterbury Bells",
                0.014036901759319619
            ],
            [
                "Foxglove",
                0.01249337052145312
            ],
            [
                "Columbine",
                0.00984475463628769
            ],
            [
                "Giant White Arum Lily",
                0.00976551631322274
            ]
        ],
        "fused_top1_prob": 0.40304315090179443,
        "fused_margin": 0.2301478385925293,
        "topk_overlap": true,
        "name_soft_agree": true,
        "img_results": [
            [
                "Canterbury Bells",
                0.8755496092091615
            ],
            [
                "Foxglove",
                0.8664124812353977
            ],
            [
                "Spring Crocus",
                0.8619786823900615
            ],
            [
                "Columbine",
                0.8473127516570015
            ],
            [
                "Giant White Arum Lily",
                0.8468446098339601
            ]
        ],
        "text_results": [
            [
                "Spring Crocus",
                0.30404079461757016
            ],
            [
                "Magnolia",
                0.28884366596550415
            ],
            [
                "Siam Tulip",
                0.2881725793297981
            ],
            [
                "Mallow",
                0.27889967844354946
            ],
            [
                "Cape Flower",
                0.26937854316833104
            ]
        ],
        "lcb_map": {
            "Spring Crocus": 0.0
        }
    },
    "need_slow_thinking": true,
    "slow_result": {
        "predicted_category": "Cyclamen persicum",
        "confidence": 0.95,
        "reasoning": "The image shows a flower with a bell-shaped structure, five overlapping petals, and a light pink color gradient that transitions to a deeper pink or purple at the base. These characteristics are consistent with the description of Cyclamen persicum. The similarity scores also indicate that Cyclamen persicum is the most closely related among the candidates, with a score of 0.3502, significantly higher than the other categories. | Key Features: The flower's bell-shaped structure, five overlapping petals, light pink color gradient, and the presence of a deep pink band at the base of each petal are key features supporting the identification as Cyclamen persicum. | Uncertainty: There are no significant uncertainty factors affecting the classification. The detailed visual characteristics match the known attributes of Cyclamen persicum, and the similarity scores further support this identification.",
        "difficulty_analysis": {
            "difficulty_reasons": [
                "The flower's petals have a gradient coloration, which can be ambiguous and may not align with typical patterns for Canterbury Bells or Spring Crocuses.",
                "The image resolution and lighting conditions may affect the clarity of distinguishing features such as petal shape and texture.",
                "The background is out of focus, which can introduce noise and distract from the flower itself."
            ],
            "key_regions": [
                "The petal edges and their curvature",
                "The color gradient from white to pink/purple",
                "The overall symmetry and structure of the flower"
            ],
            "additional_info_needed": "A clearer view of the flower's full bloom, including its stamen and pistil, would help in distinguishing it from similar species. Additionally, knowing the geographical location where the photo was taken could provide context for the specific variety of the flower."
        },
        "key_regions": [
            "The petal edges and their curvature",
            "The color gradient from white to pink/purple",
            "The overall symmetry and structure of the flower"
        ],
        "region_descriptions": [
            "The flower in the image has two prominent petals that are light pink with a subtle gradient towards a deeper pink at the base. The texture appears smooth, with a slight sheen that suggests a delicate, almost velvety surface. There are no visible patterns on the petals; they are uniformly colored.\n\nThe shape of the petals is slightly curved and pointed at the tips, giving them an elegant and graceful appearance. They are relatively large compared to the overall size of the flower, which is small and delicate. The petals are attached to a dark stem, which contrasts sharply with the lighter color of the petals.\n\nA distinctive feature is the deep pink band at the base of each petal, which adds a striking contrast to the lighter pink upper portion. This band is more pronounced and creates a clear demarcation between the two shades of pink.\n\nThe background consists of green foliage, which provides a natural and soft backdrop that enhances the delicate appearance of the flower. The overall impression is one of purity and simplicity, making it stand out against the greenery.",
            "The flower in the image exhibits a gradient coloration transitioning from white at the base to a soft pink and then to a deeper purple at the tip. The petals have a smooth texture with subtle veining visible, particularly near the edges where the color shifts more vividly. The shape is delicate and bell-like, with four distinct petals that curve slightly outward. The size appears small compared to the surrounding greenery, emphasizing its delicate nature. The flower's unique feature is the clear gradient, which sets it apart from other similar flowers that might have uniform colors or abrupt color changes. The background of lush green foliage provides a natural contrast, highlighting the flower's subtle hues and intricate details.",
            "The flower in the image is a Cyclamen persicum, characterized by its delicate and symmetrical structure. Here's a detailed description:\n\n- **Color**: The petals are primarily light pink with a subtle gradient, transitioning to a deeper pink or purple at the base. The edges of the petals have a slightly ruffled texture, adding depth and detail.\n\n- **Texture**: The petals exhibit a smooth surface with a slight sheen, possibly due to natural oils or moisture. The ruffled edges suggest a soft, almost velvety texture.\n\n- **Shape and Size**: The flower has a bell-shaped structure with five petals that are slightly overlapping. Each petal is broad at the base and tapers towards the tip, creating a graceful curve. The flower appears small to medium-sized, typical for Cyclamen species, and is positioned upright on a slender stem.\n\n- **Unique Features**: The most distinctive feature is the color gradient and the ruffled edge of the petals. Additionally, the flower's symmetry and the way the petals are arranged around the central axis contribute to its elegant appearance.\n\n- **Variations**: Cyclamen persicum flowers can vary in color intensity and petal shape, but the one in the image displays a consistent pattern across multiple blooms. The presence of a single"
        ],
        "structured_description": "### Comprehensive Description for Fine-Grained Classification\n\n#### Overall Appearance:\nThe flower in the image is a Cyclamen persicum, characterized by its delicate and symmetrical structure. It has a bell-shaped structure with five petals that are slightly overlapping. The petals are primarily light pink with a subtle gradient, transitioning to a deeper pink or purple at the base. The edges of the petals have a slightly ruffled texture, adding depth and detail. The flower appears small to medium-sized, typical for Cyclamen species, and is positioned upright on a slender stem.\n\n#### Key Region Descriptions:\n1. **Petal Edges and Curvature**:\n   - The petals are light pink with a subtle gradient towards a deeper pink at the base.\n   - The texture appears smooth, with a slight sheen suggesting a delicate, almost velvety surface.\n   - The petals are slightly curved and pointed at the tips, giving them an elegant and graceful appearance.\n   - The petals are relatively large compared to the overall size of the flower, which is small and delicate.\n   - The deep pink band at the base of each petal is more pronounced and creates a clear demarcation between the two shades of pink.\n\n2. **Color Gradient**:\n   - The petals exhibit a",
        "enhanced_results": [
            [
                "Canterbury Bells",
                0.3502198436836646
            ],
            [
                "Foxglove",
                0.3465649924941591
            ],
            [
                "Spring Crocus",
                0.34479147295602464
            ],
            [
                "Columbine",
                0.3389251006628006
            ],
            [
                "Giant White Arum Lily",
                0.3387378439335841
            ]
        ],
        "fast_result": {
            "predicted_category": "conflict",
            "confidence": 0.25186118483543396,
            "need_slow_thinking": true,
            "fused_top1": "Spring Crocus",
            "predicted_fast": "Spring Crocus",
            "img_category": "Canterbury Bells",
            "text_category": "Spring Crocus",
            "img_confidence": 0.24795114994049072,
            "text_confidence": 0.2557712197303772,
            "fused_results": [
                [
                    "Spring Crocus",
                    0.25642197262490907
                ],
                [
                    "Magnolia",
                    0.19717697655000993
                ],
                [
                    "Siam Tulip",
                    0.1952854731134952
                ],
                [
                    "Mallow",
                    0.17122837901115417
                ],
                [
                    "Cape Flower",
                    0.14962767893305193
                ],
                [
                    "Canterbury Bells",
                    0.014036901759319619
                ],
                [
                    "Foxglove",
                    0.01249337052145312
                ],
                [
                    "Columbine",
                    0.00984475463628769
                ],
                [
                    "Giant White Arum Lily",
                    0.00976551631322274
                ]
            ],
            "fused_top1_prob": 0.40304315090179443,
            "fused_margin": 0.2301478385925293,
            "topk_overlap": true,
            "name_soft_agree": true,
            "img_results": [
                [
                    "Canterbury Bells",
                    0.8755496092091615
                ],
                [
                    "Foxglove",
                    0.8664124812353977
                ],
                [
                    "Spring Crocus",
                    0.8619786823900615
                ],
                [
                    "Columbine",
                    0.8473127516570015
                ],
                [
                    "Giant White Arum Lily",
                    0.8468446098339601
                ]
            ],
            "text_results": [
                [
                    "Spring Crocus",
                    0.30404079461757016
                ],
                [
                    "Magnolia",
                    0.28884366596550415
                ],
                [
                    "Siam Tulip",
                    0.2881725793297981
                ],
                [
                    "Mallow",
                    0.27889967844354946
                ],
                [
                    "Cape Flower",
                    0.26937854316833104
                ]
            ],
            "lcb_map": {
                "Spring Crocus": 0.0
            }
        }
    },
    "mllm_judge_result": null,
    "fast_top_k": [
        [
            "Canterbury Bells",
            0.8755496092091615
        ],
        [
            "Foxglove",
            0.8664124812353977
        ],
        [
            "Spring Crocus",
            0.8619786823900615
        ],
        [
            "Columbine",
            0.8473127516570015
        ],
        [
            "Giant White Arum Lily",
            0.8468446098339601
        ],
        [
            "Spring Crocus",
            0.30404079461757016
        ],
        [
            "Magnolia",
            0.28884366596550415
        ],
        [
            "Siam Tulip",
            0.2881725793297981
        ],
        [
            "Mallow",
            0.27889967844354946
        ],
        [
            "Cape Flower",
            0.26937854316833104
        ]
    ],
    "fast_fused_results": [
        [
            "Spring Crocus",
            0.25642197262490907
        ],
        [
            "Magnolia",
            0.19717697655000993
        ],
        [
            "Siam Tulip",
            0.1952854731134952
        ],
        [
            "Mallow",
            0.17122837901115417
        ],
        [
            "Cape Flower",
            0.14962767893305193
        ]
    ],
    "timestamp": 1761937119.2401972,
    "slow_top_k": [
        [
            "Canterbury Bells",
            0.3502198436836646
        ],
        [
            "Foxglove",
            0.3465649924941591
        ],
        [
            "Spring Crocus",
            0.34479147295602464
        ],
        [
            "Columbine",
            0.3389251006628006
        ],
        [
            "Giant White Arum Lily",
            0.3387378439335841
        ]
    ]
}