{
    "query_image": "./datasets/car_196/images_discovery_all_10/006.Acura_Integra_Type_R_2001/006.Acura_Integra_Type_R_2001_07666.jpg",
    "true_category": "006.Acura Integra Type R 2001",
    "fast_result": {
        "predicted_category": "Acura Integra Type R 2001",
        "confidence": 0.8750279545783997,
        "need_slow_thinking": false,
        "fused_top1": "Acura Integra Type R 2001",
        "predicted_fast": "Acura Integra Type R 2001",
        "img_category": "Eagle Talon Hatchback 1998",
        "text_category": "Acura Integra Type R 2001",
        "img_confidence": 0.2655394971370697,
        "text_confidence": 0.396494060754776,
        "fused_results": [
            [
                "Acura Integra Type R 2001",
                0.3917272550984732
            ],
            [
                "Nissan 240SX Coupe 1998",
                0.17265237658582647
            ],
            [
                "Plymouth Neon Coupe 1999",
                0.1618733965341122
            ],
            [
                "Eagle Talon Hatchback 1998",
                0.14835059242170365
            ],
            [
                "Volkswagen Golf Hatchback 1991",
                0.1258105450295485
            ],
            [
                "Audi RS 4 Convertible 2008",
                0.007853680849075317
            ],
            [
                "Audi V8 Sedan 1994",
                0.007613162415531966
            ]
        ],
        "fused_top1_prob": 0.8750279545783997,
        "fused_margin": 0.8367599248886108,
        "topk_overlap": true,
        "name_soft_agree": true,
        "img_results": [
            [
                "Eagle Talon Hatchback 1998",
                0.8036092336380207
            ],
            [
                "Nissan 240SX Coupe 1998",
                0.7995329336654762
            ],
            [
                "Acura Integra Type R 2001",
                0.79553911248064
            ],
            [
                "Audi RS 4 Convertible 2008",
                0.7513274523122856
            ],
            [
                "Audi V8 Sedan 1994",
                0.7488763134593617
            ]
        ],
        "text_results": [
            [
                "Acura Integra Type R 2001",
                0.34064409394422923
            ],
            [
                "Plymouth Neon Coupe 1999",
                0.2808243893856577
            ],
            [
                "Nissan 240SX Coupe 1998",
                0.27935266417731897
            ],
            [
                "Eagle Talon Hatchback 1998",
                0.26717645992126643
            ],
            [
                "Volkswagen Golf Hatchback 1991",
                0.26302145931270593
            ]
        ],
        "lcb_map": {
            "Acura Integra Type R 2001": 0.0
        }
    },
    "need_slow_thinking": false,
    "slow_result": null,
    "mllm_judge_result": null,
    "fast_top_k": [
        [
            "Eagle Talon Hatchback 1998",
            0.8036092336380207
        ],
        [
            "Nissan 240SX Coupe 1998",
            0.7995329336654762
        ],
        [
            "Acura Integra Type R 2001",
            0.79553911248064
        ],
        [
            "Audi RS 4 Convertible 2008",
            0.7513274523122856
        ],
        [
            "Audi V8 Sedan 1994",
            0.7488763134593617
        ],
        [
            "Acura Integra Type R 2001",
            0.34064409394422923
        ],
        [
            "Plymouth Neon Coupe 1999",
            0.2808243893856577
        ],
        [
            "Nissan 240SX Coupe 1998",
            0.27935266417731897
        ],
        [
            "Eagle Talon Hatchback 1998",
            0.26717645992126643
        ],
        [
            "Volkswagen Golf Hatchback 1991",
            0.26302145931270593
        ]
    ],
    "fast_fused_results": [
        [
            "Acura Integra Type R 2001",
            0.3917272550984732
        ],
        [
            "Nissan 240SX Coupe 1998",
            0.17265237658582647
        ],
        [
            "Plymouth Neon Coupe 1999",
            0.1618733965341122
        ],
        [
            "Eagle Talon Hatchback 1998",
            0.14835059242170365
        ],
        [
            "Volkswagen Golf Hatchback 1991",
            0.1258105450295485
        ]
    ],
    "timestamp": 1762013039.5601866
}