{
    "query_image": "./datasets/car_196/images_discovery_all_10/023.Audi_S4_Sedan_2012/023.Audi_S4_Sedan_2012_05824.jpg",
    "true_category": "023.Audi S4 Sedan 2012",
    "fast_result": {
        "predicted_category": "conflict",
        "confidence": 0.26349078863859177,
        "need_slow_thinking": true,
        "fused_top1": "BMW 3 Series Wagon 2012",
        "predicted_fast": "BMW 3 Series Wagon 2012",
        "img_category": "BMW M3 Coupe 2012",
        "text_category": "BMW 3 Series Wagon 2012",
        "img_confidence": 0.3157537281513214,
        "text_confidence": 0.21122784912586212,
        "fused_results": [
            [
                "BMW 3 Series Wagon 2012",
                0.2023058009318641
            ],
            [
                "Audi V8 Sedan 1994",
                0.19956454490461656
            ],
            [
                "Audi S4 Sedan 2012",
                0.19911292949839243
            ],
            [
                "Audi A5 Coupe 2012",
                0.1813282772898674
            ],
            [
                "Audi S4 Sedan 2007",
                0.17562898630133042
            ],
            [
                "BMW M3 Coupe 2012",
                0.017427030669861152
            ],
            [
                "Dodge Magnum Wagon 2008",
                0.012377281535056331
            ],
            [
                "Chevrolet Impala Sedan 2007",
                0.009686476086813306
            ],
            [
                "Acura RL Sedan 2012",
                0.009295741468667984
            ],
            [
                "Chrysler PT Cruiser Convertible 2008",
                0.009153981598523948
            ]
        ],
        "fused_top1_prob": 0.2141604870557785,
        "fused_margin": 0.008224591612815857,
        "topk_overlap": false,
        "name_soft_agree": false,
        "img_results": [
            [
                "BMW M3 Coupe 2012",
                0.8400891660802652
            ],
            [
                "Dodge Magnum Wagon 2008",
                0.8132799701099123
            ],
            [
                "Chevrolet Impala Sedan 2007",
                0.7933663709803966
            ],
            [
                "Acura RL Sedan 2012",
                0.7901299650875084
            ],
            [
                "Chrysler PT Cruiser Convertible 2008",
                0.7890561751712871
            ]
        ],
        "text_results": [
            [
                "BMW 3 Series Wagon 2012",
                0.28769887115242687
            ],
            [
                "Audi V8 Sedan 1994",
                0.2867453591813465
            ],
            [
                "Audi S4 Sedan 2012",
                0.286594572825249
            ],
            [
                "Audi A5 Coupe 2012",
                0.2799996041167101
            ],
            [
                "Audi S4 Sedan 2007",
                0.2777540790708276
            ]
        ],
        "lcb_map": {
            "BMW 3 Series Wagon 2012": 0.0
        }
    },
    "need_slow_thinking": true,
    "slow_result": {
        "predicted_category": "Acura RL Sedan 2012",
        "confidence": 0.95,
        "reasoning": "The image shows a white sedan with a sleek and modern design, consistent with the Acura RL Sedan. The taillight design, grille shape, and overall body style align closely with the Acura RL. The similarity score to the Acura RL is the highest among the candidates, indicating a strong match. The other models, such as the BMW M3, Dodge Magnum, and Chevrolet Impala, have distinct features that do not match the observed characteristics in the image. | Key Features: Sleek white sedan design, taillight shape, grille style, and overall body proportions | Uncertainty: The resolution of the image slightly affects the clarity of some details, which could potentially lead to minor misinterpretations. However, the overall design elements strongly support the Acura RL classification.",
        "difficulty_analysis": {
            "difficulty_reasons": [
                "The car's model and brand are not clearly visible due to the angle and lighting.",
                "The image resolution is low, which affects the clarity of distinguishing features.",
                "There is a lack of distinct branding or model-specific elements that are typically used for accurate classification."
            ],
            "key_regions": [
                "The rear badge area to identify the manufacturer and model year.",
                "The front grille and headlights to confirm the brand and model.",
                "The side profile to check for any unique design elements that could differentiate it from other models."
            ],
            "additional_info_needed": "A clearer image with better resolution and more visible details such as the rear badge, front grille, and any unique design features."
        },
        "key_regions": [
            "The rear badge area to identify the manufacturer and model year.",
            "The front grille and headlights to confirm the brand and model.",
            "The side profile to check for any unique design elements that could differentiate it from other models."
        ],
        "region_descriptions": [
            "The rear badge area of the car in the image is located near the center of the trunk lid, just above the taillights. It is a rectangular shape with a metallic finish, giving it a reflective appearance. The badge itself appears to be silver or chrome, which contrasts with the white paint of the car. The text on the badge is not clearly legible due to the resolution of the image, but it typically includes the manufacturer's logo and the model year. The badge is relatively small compared to the overall size of the car, making it a subtle yet identifiable feature. There are no visible variations or special characteristics in the badge that stand out; it follows a standard design for luxury vehicles like the one shown.",
            "The vehicle in the image is an Audi A4, identifiable by its distinct grille and headlight design. Here's a breakdown of the visual characteristics:\n\n1. **Grille:**\n   - **Color:** The grille appears to be silver or chrome, which is typical for Audi vehicles.\n   - **Texture:** It has a smooth, polished finish with a subtle grid pattern.\n   - **Shape and Size:** The grille is large and prominently positioned at the front of the car, spanning across the width of the hood. It is integrated into the front bumper and is flanked by the headlights.\n\n2. **Headlights:**\n   - **Shape:** The headlights are rectangular with a slightly curved top edge, a common design feature in Audi models.\n   - **Size:** They are relatively large compared to the overall size of the car, contributing to the vehicle's sleek and modern appearance.\n   - **Color:** The headlights appear to have a clear lens, with no visible tinting or coloration.\n   - **Unique Features:** The headlights are likely LED or xenon, as they are characteristic of newer Audi models. There may be a subtle daytime running light (DRL) feature integrated into the lower part of the headlights.\n\n3. **Other Characteristics:**\n  ",
            "The image shows a white sedan with a sleek and modern design. Here are the key visual characteristics that could differentiate this vehicle:\n\n1. **Color and Texture**: The car is painted in a glossy white finish, which reflects light and gives it a clean, polished appearance. There are no visible textures or patterns on the bodywork, maintaining a smooth surface.\n\n2. **Shape and Size**: The sedan has a compact yet elongated shape typical of mid-size vehicles. It appears to be slightly longer than a compact car but shorter than a full-size sedan. The proportions are balanced, with a long hood and a short rear deck, suggesting a sporty yet practical design.\n\n3. **Unique or Distinctive Features**:\n   - **Rear Design**: The taillights are horizontally oriented and feature a distinctive LED design, which is characteristic of Audi's styling language. They are integrated into the rear bumper, giving a cohesive look.\n   - **Wheels**: The wheels have a multi-spoke alloy design with a silver finish, which adds a touch of elegance and sportiness to the overall look.\n   - **Side Profile**: The side profile showcases a smooth line with subtle curves, emphasizing a streamlined silhouette. The windows are tinted, providing privacy while also contributing to"
        ],
        "structured_description": "### Comprehensive Description for Fine-Grained Classification\n\n#### Overall Appearance:\nThe vehicle in the image is a white sedan with a sleek and modern design, indicative of a mid-size luxury car. The car exhibits a clean and polished look with a glossy white paint job that reflects light, enhancing its aesthetic appeal. The proportions are balanced, with a long hood and a short rear deck, suggesting a sporty yet practical design.\n\n#### Rear Badge Area:\n- **Location:** Near the center of the trunk lid, just above the taillights.\n- **Shape:** Rectangular with a metallic finish, giving it a reflective appearance.\n- **Material:** Likely silver or chrome, contrasting with the white paint.\n- **Text:** The text on the badge is not clearly legible due to the resolution of the image, but it typically includes the manufacturer's logo and the model year.\n- **Design:** Standard for luxury vehicles, with no visible special characteristics.\n\n#### Front Grille and Headlights:\n- **Grille:**\n  - **Color:** Silver or chrome.\n  - **Texture:** Smooth, polished finish with a subtle grid pattern.\n  - **Shape and Size:** Large and prominently positioned, spanning across the width of the hood.\n  - **Position:** Integrated into the",
        "enhanced_results": [
            [
                "BMW M3 Coupe 2012",
                0.3360356664321061
            ],
            [
                "Dodge Magnum Wagon 2008",
                0.32531198804396494
            ],
            [
                "Chevrolet Impala Sedan 2007",
                0.3173465483921587
            ],
            [
                "Acura RL Sedan 2012",
                0.3160519860350034
            ],
            [
                "Chrysler PT Cruiser Convertible 2008",
                0.31562247006851485
            ]
        ],
        "fast_result": {
            "predicted_category": "conflict",
            "confidence": 0.26349078863859177,
            "need_slow_thinking": true,
            "fused_top1": "BMW 3 Series Wagon 2012",
            "predicted_fast": "BMW 3 Series Wagon 2012",
            "img_category": "BMW M3 Coupe 2012",
            "text_category": "BMW 3 Series Wagon 2012",
            "img_confidence": 0.3157537281513214,
            "text_confidence": 0.21122784912586212,
            "fused_results": [
                [
                    "BMW 3 Series Wagon 2012",
                    0.2023058009318641
                ],
                [
                    "Audi V8 Sedan 1994",
                    0.19956454490461656
                ],
                [
                    "Audi S4 Sedan 2012",
                    0.19911292949839243
                ],
                [
                    "Audi A5 Coupe 2012",
                    0.1813282772898674
                ],
                [
                    "Audi S4 Sedan 2007",
                    0.17562898630133042
                ],
                [
                    "BMW M3 Coupe 2012",
                    0.017427030669861152
                ],
                [
                    "Dodge Magnum Wagon 2008",
                    0.012377281535056331
                ],
                [
                    "Chevrolet Impala Sedan 2007",
                    0.009686476086813306
                ],
                [
                    "Acura RL Sedan 2012",
                    0.009295741468667984
                ],
                [
                    "Chrysler PT Cruiser Convertible 2008",
                    0.009153981598523948
                ]
            ],
            "fused_top1_prob": 0.2141604870557785,
            "fused_margin": 0.008224591612815857,
            "topk_overlap": false,
            "name_soft_agree": false,
            "img_results": [
                [
                    "BMW M3 Coupe 2012",
                    0.8400891660802652
                ],
                [
                    "Dodge Magnum Wagon 2008",
                    0.8132799701099123
                ],
                [
                    "Chevrolet Impala Sedan 2007",
                    0.7933663709803966
                ],
                [
                    "Acura RL Sedan 2012",
                    0.7901299650875084
                ],
                [
                    "Chrysler PT Cruiser Convertible 2008",
                    0.7890561751712871
                ]
            ],
            "text_results": [
                [
                    "BMW 3 Series Wagon 2012",
                    0.28769887115242687
                ],
                [
                    "Audi V8 Sedan 1994",
                    0.2867453591813465
                ],
                [
                    "Audi S4 Sedan 2012",
                    0.286594572825249
                ],
                [
                    "Audi A5 Coupe 2012",
                    0.2799996041167101
                ],
                [
                    "Audi S4 Sedan 2007",
                    0.2777540790708276
                ]
            ],
            "lcb_map": {
                "BMW 3 Series Wagon 2012": 0.0
            }
        }
    },
    "mllm_judge_result": null,
    "fast_top_k": [
        [
            "BMW M3 Coupe 2012",
            0.8400891660802652
        ],
        [
            "Dodge Magnum Wagon 2008",
            0.8132799701099123
        ],
        [
            "Chevrolet Impala Sedan 2007",
            0.7933663709803966
        ],
        [
            "Acura RL Sedan 2012",
            0.7901299650875084
        ],
        [
            "Chrysler PT Cruiser Convertible 2008",
            0.7890561751712871
        ],
        [
            "BMW 3 Series Wagon 2012",
            0.28769887115242687
        ],
        [
            "Audi V8 Sedan 1994",
            0.2867453591813465
        ],
        [
            "Audi S4 Sedan 2012",
            0.286594572825249
        ],
        [
            "Audi A5 Coupe 2012",
            0.2799996041167101
        ],
        [
            "Audi S4 Sedan 2007",
            0.2777540790708276
        ]
    ],
    "fast_fused_results": [
        [
            "BMW 3 Series Wagon 2012",
            0.2023058009318641
        ],
        [
            "Audi V8 Sedan 1994",
            0.19956454490461656
        ],
        [
            "Audi S4 Sedan 2012",
            0.19911292949839243
        ],
        [
            "Audi A5 Coupe 2012",
            0.1813282772898674
        ],
        [
            "Audi S4 Sedan 2007",
            0.17562898630133042
        ]
    ],
    "timestamp": 1762016107.5285995,
    "slow_top_k": [
        [
            "BMW M3 Coupe 2012",
            0.3360356664321061
        ],
        [
            "Dodge Magnum Wagon 2008",
            0.32531198804396494
        ],
        [
            "Chevrolet Impala Sedan 2007",
            0.3173465483921587
        ],
        [
            "Acura RL Sedan 2012",
            0.3160519860350034
        ],
        [
            "Chrysler PT Cruiser Convertible 2008",
            0.31562247006851485
        ]
    ]
}